Metadata-Version: 1.0
Name: wznpackage
Version: 1.0.0
Summary: mypackage_by_ZW
Home-page: https://github.com
Author: Zhining
Author-email: w_zhining@163.com
License: UNKNOWN
Platform: UNKNOWN
